billing/__init__.py
billing/availability.py
billing/coupon.py
billing/credit.py
billing/credit_note.py
billing/customer.py
billing/event.py
billing/invoice.py
billing/plan.py
billing/sdk.py
billing/sdkconfiguration.py
billing/subscription.py
billing/models/__init__.py
billing/models/errors/__init__.py
billing/models/errors/requestvalidationerror.py
billing/models/errors/sdkerror.py
billing/models/errors/validationerrors.py
billing/models/operations/__init__.py
billing/models/operations/add_ledger_entry_external_id.py
billing/models/operations/amend_event.py
billing/models/operations/amend_usage.py
billing/models/operations/amend_usage_external_customer_id.py
billing/models/operations/archive_coupon.py
billing/models/operations/cancel_subscription.py
billing/models/operations/close_backfill.py
billing/models/operations/create_backfill.py
billing/models/operations/create_coupon.py
billing/models/operations/create_customer.py
billing/models/operations/create_customer_balance_transaction.py
billing/models/operations/create_invoice_line_item.py
billing/models/operations/create_ledger_entry.py
billing/models/operations/create_subscription.py
billing/models/operations/delete_customer.py
billing/models/operations/deprecate_event.py
billing/models/operations/fetch_coupon.py
billing/models/operations/fetch_credit_note.py
billing/models/operations/fetch_customer.py
billing/models/operations/fetch_customer_costs.py
billing/models/operations/fetch_customer_costs_external_id.py
billing/models/operations/fetch_customer_credits.py
billing/models/operations/fetch_customer_credits_external_id.py
billing/models/operations/fetch_customer_credits_ledger.py
billing/models/operations/fetch_customer_credits_ledger_external_id.py
billing/models/operations/fetch_customer_external_id.py
billing/models/operations/fetch_invoice.py
billing/models/operations/fetch_plan.py
billing/models/operations/fetch_plan_external_id.py
billing/models/operations/fetch_subscription.py
speakeasy_billing-0.5.0.dist-info/LICENSE.md
speakeasy_billing-0.5.0.dist-info/METADATA
speakeasy_billing-0.5.0.dist-info/WHEEL
speakeasy_billing-0.5.0.dist-info/top_level.txt
speakeasy_billing-0.5.0.dist-info/RECORD
